{
    "id": "f879223d-d69d-45e6-a9e9-02e3bcd8f49d",
    "status": "Started",
    "decModel": "MockDecision",
    "diagModel": "MockDiag",
    "disease": "Post Traumatic Stress Disorder",
    "diagnosticProcessHistory": [
        {
            "nodeId": "3c635aca-bac9-4cb4-aabe-e528039934af",
            "stage": "0",
            "descr": "Stage 0",
            "diseaseProbability": "0",
            "severity": "Low",
            "response": "The estimated disease probability is Low (0)",
            "actions": [
                {
                    "descr": "No survey here, just complete",
                    "question": false,
                    "questionnaireId": "801fa8c1-4285-42c5-acfd-3adcd3ea644b",
                    "actionId": "99f9e1a5-ef8c-432d-8260-abdc87b39469",
                    "numQuestions": "1",
                    "utility": "0.0",
                    "utilityLevel": "Low",
                    "status": "Not Started"
                },
                {
                    "descr": "Domestic Violence Questionnaire",
                    "question": false,
                    "questionnaireId": "cfbcdd52-1faf-4931-b705-e014a957c0f2",
                    "actionId": "c13139a6-0706-4b94-be81-38c7e99bd47c",
                    "numQuestions": "1",
                    "utility": "0.4",
                    "utilityLevel": "Low",
                    "status": "Not Started",
                    "statusUpdated": "10/14/11 1:39 PM"
                },
                {
                    "descr": "Ask for alcohol abuse",
                    "question": "ul",
                    "questionnaireId": "54209e03-5c96-47bc-a6d3-b2bef4b298df",
                    "actionId": "b8a8ab59-9e12-4fc5-b778-6ac1596b8e99",
                    "numQuestions": "1",
                    "utility": "0.51",
                    "utilityLevel": "Normal",
                    "status": "Not Started"
                },
                {
                    "descr": "No survey here, just complete",
                    "question": false,
                    "questionnaireId": "a72b1567-28a4-4dfa-b0af-277eb57b2bd0",
                    "actionId": "fb0f7193-6d41-44c6-a9a1-afdb0b50a7b1",
                    "numQuestions": "1",
                    "utility": "0.51",
                    "utilityLevel": "Normal",
                    "statusUpdated": "02/17/2012 1:39 PM",
                    "status": "Complete"
                }
            ]
        },
        {
            "nodeId": "3c635aca-bacasdf9-4cb4-aabe-e528039934af",
            "stage": "1",
            "current": true,
            "descr": "Stage 1",
            "diseaseProbability": "20",
            "severity": "Average",
            "response": "The estimated disease probability is Average(20)",
            "actions": [
                {
                    "descr": "No survey here, just complete",
                    "question": false,
                    "questionnaireId": "801fa8casdf1-4285-42c5-acfd-3adcd3ea644b",
                    "actionId": "99f9e1a5-ef8c-432d-sdfg8260-abdc87b39469",
                    "numQuestions": "1",
                    "utility": "0.0",
                    "utilityLevel": "Low",
                    "status": "Not Started"
                },
                {
                    "descr": "No survey here, just complete",
                    "question": false,
                    "questionnaireId": "cfbcdd52-1faf-4931-b7sdfg05-e014a957c0f2",
                    "actionId": "c13139a6-0706-4b94-be81-38c7e2354699bd47c",
                    "numQuestions": "1",
                    "utility": "0.4",
                    "utilityLevel": "Normal",
                    "status": "Complete",
                    "statusUpdated": "10/14/11 1:39 PM"
                },
                {
                    "descr": "Ask for alcohol abuse",
                    "question": "ul",
                    "questionnaireId": "54209e03-sdfg5c96-47bc-a6d3-b2bef4b298df",
                    "actionId": "b8a8ab59-9sdfge12-4fc5-b778-h",
                    "numQuestions": "1",
                    "utility": "0.51",
                    "utilityLevel": "Normal",
                    "status": "Not Started"
                },
                {
                    "descr": "No survey here, just complete",
                    "question": false,
                    "questionnaireId": "a72bfdg1567-28a4-4dfa-b0af-277eb57b2bd0",
                    "actionId": "fb0f7193-6d41-44c6assdf-a9a1-afdb0b50a7b1",
                    "numQuestions": "1",
                    "utility": "0.51",
                    "utilityLevel": "Normal",
                    "status": "Not Started"
                },
                {
                    "descr": "Ask for number of deployments ",
                    "questionnaireId": "0d6esdfga4bb-cb8f-478a-99fd-106c2b62ef30",
                    "actionId": "94fdba27-bsdf7c2-42c1-ad62-4dfdea0e09af",
                    "numQuestions": "1",
                    "utility": "0.02",
                    "utilityLevel": "Low",
                    "status": "Not Started"
                },
                {
                    "descr": "Suggested Option",
                    "question": false,
                    "questionnaireId": "3b932930-4b0b-423c-aba2-64e9e486e7fa",
                    "actionId": "fc88ced8-5c39-4faa-b90d-ff9f8c28a5e4",
                    "numQuestions": "1",
                    "utility": "0.99",
                    "utilityLevel": "Normal",
                    "status": "Not Started"
                },
                {
                    "descr": "You had better not know",
                    "confirm": false,
                    "questionnaireId": "87e20f5b-fa92-4jfhg957-b703-71b277ad9841",
                    "actionId": "da58f128-06f2-4adfg54867-874d-ddfd1bba57cc",
                    "numQuestions": "1",
                    "utility": "0.56",
                    "utilityLevel": "Normal",
                    "status": "Not Started"
                }
            ]
        }
    ],
    "canAdvance": false,
    "canCancel": true,
    "actions": [
        "org.kmr2.decision.impl.AskSomething6",
        "org.kmr2.decision.impl.AskSomething5",
        "org.kmr2.decision.impl.AskSomething7",
        "org.kmr2.decision.impl.AskAlcohol",
        "org.kmr2.decision.impl.AskSomething4",
        "org.kmr2.decision.impl.AskDeployment",
        "org.kmr2.decision.impl.DoExcruciatinglyPainfulTest",
        "org.kmr2.decision.impl.AskSomething2",
        "org.kmr2.decision.impl.AskSomething8",
        "org.kmr2.decision.impl.AskSomething1",
        "org.kmr2.decision.impl.AskSomething3"
    ],
    "successStatus": true
}